odoo/addons/delivery_price_rule_volumetric_weight/README.rst
odoo/addons/delivery_price_rule_volumetric_weight/__init__.py
odoo/addons/delivery_price_rule_volumetric_weight/__manifest__.py
odoo/addons/delivery_price_rule_volumetric_weight/i18n/delivery_price_rule_volumetric_weight.pot
odoo/addons/delivery_price_rule_volumetric_weight/i18n/es.po
odoo/addons/delivery_price_rule_volumetric_weight/models/__init__.py
odoo/addons/delivery_price_rule_volumetric_weight/models/delivery_carrier.py
odoo/addons/delivery_price_rule_volumetric_weight/models/delivery_price_rule.py
odoo/addons/delivery_price_rule_volumetric_weight/readme/CONFIGURE.rst
odoo/addons/delivery_price_rule_volumetric_weight/readme/CONTRIBUTORS.rst
odoo/addons/delivery_price_rule_volumetric_weight/readme/DESCRIPTION.rst
odoo/addons/delivery_price_rule_volumetric_weight/readme/USAGE.rst
odoo/addons/delivery_price_rule_volumetric_weight/static/description/icon.png
odoo/addons/delivery_price_rule_volumetric_weight/static/description/index.html
odoo/addons/delivery_price_rule_volumetric_weight/tests/__init__.py
odoo/addons/delivery_price_rule_volumetric_weight/tests/test_delivery_price.py
odoo13_addon_delivery_price_rule_volumetric_weight-13.0.2.0.0.dist-info/METADATA
odoo13_addon_delivery_price_rule_volumetric_weight-13.0.2.0.0.dist-info/WHEEL
odoo13_addon_delivery_price_rule_volumetric_weight-13.0.2.0.0.dist-info/top_level.txt
odoo13_addon_delivery_price_rule_volumetric_weight-13.0.2.0.0.dist-info/RECORD
